ordal_autohire_firebase/__init__.py
ordal_autohire_firebase/__main__.py
ordal_autohire_firebase/main.py
ordal_autohire_firebase/poke_tools.py
ordal_autohire_firebase/server.py
ordal_autohire_firebase/services/__init__.py
ordal_autohire_firebase/services/firebase_client.py
ordal_autohire_firebase/services/init_firebase_server.py
ordal_autohire_firebase/services/mcp_profile_helpers.py
ordal_autohire_firebase/services/seed_firebase_db.py
ordal_autohire_firebase_server-0.1.11.dist-info/METADATA
ordal_autohire_firebase_server-0.1.11.dist-info/WHEEL
ordal_autohire_firebase_server-0.1.11.dist-info/entry_points.txt
ordal_autohire_firebase_server-0.1.11.dist-info/RECORD
