Metadata-Version: 2.4
Name: ordal-autohire-firebase-server
Version: 0.1.11
Summary: Ordal AutoHire Firebase-backed MCP server & tools
Project-URL: Homepage, https://github.com/youruser/ordal-autohire-firebase-server
Author: Obie Ananda
License: MIT
Requires-Python: >=3.12
Requires-Dist: firebase-admin<7,>=6.0
Requires-Dist: google-cloud-firestore<3,>=2.16
Requires-Dist: pydantic>=2.6
Requires-Dist: python-dotenv>=1.0
Requires-Dist: smolagents[mcp]>=1.21.2
Requires-Dist: typing-extensions>=4.9
